odoo/addons/ssi_transaction_mixin/README.rst
odoo/addons/ssi_transaction_mixin/__init__.py
odoo/addons/ssi_transaction_mixin/__manifest__.py
odoo/addons/ssi_transaction_mixin/menu.xml
odoo/addons/ssi_transaction_mixin/i18n/ssi_transaction_mixin.pot
odoo/addons/ssi_transaction_mixin/models/__init__.py
odoo/addons/ssi_transaction_mixin/models/mixin_transaction.py
odoo/addons/ssi_transaction_mixin/static/description/icon.png
odoo/addons/ssi_transaction_mixin/views/mixin_transaction_views.xml
odoo14_addon_ssi_transaction_mixin-14.0.4.15.0.dist-info/METADATA
odoo14_addon_ssi_transaction_mixin-14.0.4.15.0.dist-info/WHEEL
odoo14_addon_ssi_transaction_mixin-14.0.4.15.0.dist-info/top_level.txt
odoo14_addon_ssi_transaction_mixin-14.0.4.15.0.dist-info/RECORD
